azure/mgmt/datamigration/__init__.py
azure/mgmt/datamigration/_configuration.py
azure/mgmt/datamigration/_data_migration_management_client.py
azure/mgmt/datamigration/_version.py
azure/mgmt/datamigration/aio/__init__.py
azure/mgmt/datamigration/aio/_configuration.py
azure/mgmt/datamigration/aio/_data_migration_management_client.py
azure/mgmt/datamigration/aio/operations/__init__.py
azure/mgmt/datamigration/aio/operations/_files_operations.py
azure/mgmt/datamigration/aio/operations/_operations.py
azure/mgmt/datamigration/aio/operations/_projects_operations.py
azure/mgmt/datamigration/aio/operations/_resource_skus_operations.py
azure/mgmt/datamigration/aio/operations/_service_tasks_operations.py
azure/mgmt/datamigration/aio/operations/_services_operations.py
azure/mgmt/datamigration/aio/operations/_tasks_operations.py
azure/mgmt/datamigration/aio/operations/_usages_operations.py
azure/mgmt/datamigration/models/__init__.py
azure/mgmt/datamigration/models/_data_migration_management_client_enums.py
azure/mgmt/datamigration/models/_models.py
azure/mgmt/datamigration/models/_models_py3.py
azure/mgmt/datamigration/operations/__init__.py
azure/mgmt/datamigration/operations/_files_operations.py
azure/mgmt/datamigration/operations/_operations.py
azure/mgmt/datamigration/operations/_projects_operations.py
azure/mgmt/datamigration/operations/_resource_skus_operations.py
azure/mgmt/datamigration/operations/_service_tasks_operations.py
azure/mgmt/datamigration/operations/_services_operations.py
azure/mgmt/datamigration/operations/_tasks_operations.py
azure/mgmt/datamigration/operations/_usages_operations.py
azure_mgmt_datamigration-9.0.0.dist-info/METADATA
azure_mgmt_datamigration-9.0.0.dist-info/WHEEL
azure_mgmt_datamigration-9.0.0.dist-info/top_level.txt
azure_mgmt_datamigration-9.0.0.dist-info/RECORD
